noxfile.py
GeoTier/geo_tier.py
GeoTier/geo_tier_config.py
GeoTier/geo_tier_engine.py
GeoTier/spatial_index.py
docs/source/conf.py
geotier-1.2.1.dist-info/licenses/LICENSE
tests/test_tier_engine.py
geotier-1.2.1.dist-info/METADATA
geotier-1.2.1.dist-info/WHEEL
geotier-1.2.1.dist-info/entry_points.txt
geotier-1.2.1.dist-info/top_level.txt
geotier-1.2.1.dist-info/RECORD
