Metadata-Version: 2.4
Name: GeoTier
Version: 1.2.1
Summary: Assigns features to hierarchical tiers based on score and spatial separation.
Author: corb
License: Copyright 2025 corb555
Project-URL: Repository, https://github.com/corb555/GeoTier
Keywords: gis,geospatial,cartography,decluttering,classification,ranking
Classifier: Development Status :: 4 - Beta
Classifier: Intended Audience :: Developers
Classifier: Intended Audience :: Science/Research
Classifier: License :: OSI Approved :: MIT License
Classifier: Operating System :: POSIX :: Linux
Classifier: Operating System :: MacOS
Classifier: Programming Language :: Python :: 3.9
Classifier: Programming Language :: Python :: 3.10
Classifier: Programming Language :: Python :: 3.11
Classifier: Topic :: Scientific/Engineering :: GIS
Classifier: Topic :: Software Development :: Libraries :: Python Modules
Requires-Python: >=3.9
License-File: LICENSE
Requires-Dist: pandas~=2.2.3
Requires-Dist: geopandas
Requires-Dist: shapely~=2.1.0
Requires-Dist: YMLEditor~=1.0
Requires-Dist: numpy
Requires-Dist: rtree~=1.4.1
Provides-Extra: test
Requires-Dist: pytest>=6.0; extra == "test"
Requires-Dist: pytest-mock; extra == "test"
Requires-Dist: mypy; extra == "test"
Requires-Dist: ruff; extra == "test"
Requires-Dist: coverage[toml]; extra == "test"
Requires-Dist: nox; extra == "test"
Provides-Extra: docs
Requires-Dist: sphinx; extra == "docs"
Requires-Dist: furo; extra == "docs"
Dynamic: license-file
